example/__init__.py
example/declare.py
example/run_this_one.py
example/versions/__init__.py
example/versions/main.py
flask_version/__init__.py
flask_version/flask_version.py
flask_version/utils.py
flask_version/version_dispatcher.py
flask_version/exceptions/__init__.py
flask_version/exceptions/stop_match.py
flask_version/exceptions/version_identifier.py
flask_version/interfaces/__init__.py
flask_version/interfaces/version_config.py
flask_version/meta/__init__.py
flask_version/meta/singleton.py
unittests_env/__init__.py
unittests_env/endpoints.py
unittests_env/make_app.py
unittests_env/versions/__init__.py
unittests_env/versions/endpoint_a.py
unittests_env/versions/endpoint_b.py
itay_bardugo_flask_version-1.0.2.dist-info/LICENSE
itay_bardugo_flask_version-1.0.2.dist-info/METADATA
itay_bardugo_flask_version-1.0.2.dist-info/WHEEL
itay_bardugo_flask_version-1.0.2.dist-info/top_level.txt
itay_bardugo_flask_version-1.0.2.dist-info/RECORD
