Metadata-Version: 2.1
Name: itay-bardugo-flask-version
Version: 1.0.2
Summary: a package to handle flask routes endpoints by versions
Home-page: https://github.com/itay-bardugo/flask_version
Author: Itay Bardugo
Author-email: itaybardugo91@gmail.com
License: UNKNOWN
Platform: UNKNOWN
Classifier: Programming Language :: Python :: 3
Classifier: License :: OSI Approved :: MIT License
Classifier: Operating System :: OS Independent
Requires-Python: >=3.6
